COPYING
COPYING.LESSER
MANIFEST.in
README.md
setup.cfg
setup.py
bin/dramatiq-gevent
dramatiq/__init__.py
dramatiq/__main__.py
dramatiq/actor.py
dramatiq/asyncio.py
dramatiq/broker.py
dramatiq/canteen.py
dramatiq/cli.py
dramatiq/common.py
dramatiq/compat.py
dramatiq/composition.py
dramatiq/encoder.py
dramatiq/errors.py
dramatiq/generic.py
dramatiq/logging.py
dramatiq/message.py
dramatiq/py.typed
dramatiq/test.py
dramatiq/threading.py
dramatiq/watcher.py
dramatiq/worker.py
dramatiq/brokers/__init__.py
dramatiq/brokers/rabbitmq.py
dramatiq/brokers/redis.py
dramatiq/brokers/stub.py
dramatiq/brokers/redis/dispatch.lua
dramatiq/brokers/redis/maxstack.lua
dramatiq/middleware/__init__.py
dramatiq/middleware/age_limit.py
dramatiq/middleware/asyncio.py
dramatiq/middleware/callbacks.py
dramatiq/middleware/current_message.py
dramatiq/middleware/group_callbacks.py
dramatiq/middleware/middleware.py
dramatiq/middleware/pipelines.py
dramatiq/middleware/prometheus.py
dramatiq/middleware/retries.py
dramatiq/middleware/shutdown.py
dramatiq/middleware/threading.py
dramatiq/middleware/time_limit.py
dramatiq/rate_limits/__init__.py
dramatiq/rate_limits/backend.py
dramatiq/rate_limits/barrier.py
dramatiq/rate_limits/bucket.py
dramatiq/rate_limits/concurrent.py
dramatiq/rate_limits/rate_limiter.py
dramatiq/rate_limits/window.py
dramatiq/rate_limits/backends/__init__.py
dramatiq/rate_limits/backends/memcached.py
dramatiq/rate_limits/backends/redis.py
dramatiq/rate_limits/backends/stub.py
dramatiq/results/__init__.py
dramatiq/results/backend.py
dramatiq/results/errors.py
dramatiq/results/middleware.py
dramatiq/results/result.py
dramatiq/results/backends/__init__.py
dramatiq/results/backends/memcached.py
dramatiq/results/backends/redis.py
dramatiq/results/backends/stub.py
dramatiq_spielbergs.egg-info/PKG-INFO
dramatiq_spielbergs.egg-info/SOURCES.txt
dramatiq_spielbergs.egg-info/dependency_links.txt
dramatiq_spielbergs.egg-info/entry_points.txt
dramatiq_spielbergs.egg-info/requires.txt
dramatiq_spielbergs.egg-info/top_level.txt
tests/test_actors.py
tests/test_barrier.py
tests/test_broker.py
tests/test_bucket_rate_limiter.py
tests/test_callbacks.py
tests/test_canteen.py
tests/test_cli.py
tests/test_common.py
tests/test_composition.py
