Metadata-Version: 2.1
Name: dramatiq-spielbergs
Version: 1.14.5
Summary: Background Processing for Python 3.
Author: Bogdan Popa
Author-email: bogdan@cleartype.io
Project-URL: Documentation, https://dramatiq.io
Project-URL: Source, https://github.com/Bogdanp/dramatiq
Classifier: Programming Language :: Python :: 3.7
Classifier: Programming Language :: Python :: 3.8
Classifier: Programming Language :: Python :: 3.9
Classifier: Programming Language :: Python :: 3.10
Classifier: Programming Language :: Python :: 3.11
Classifier: Programming Language :: Python :: 3 :: Only
Classifier: Topic :: System :: Distributed Computing
Classifier: License :: OSI Approved :: GNU Lesser General Public License v3 or later (LGPLv3+)
Requires-Python: >=3.7
Provides-Extra: gevent
Provides-Extra: memcached
Provides-Extra: rabbitmq
Provides-Extra: redis
Provides-Extra: watch
Provides-Extra: all
Provides-Extra: dev
License-File: COPYING
License-File: COPYING.LESSER
